{"properties": [
  {
    "name": "app.token-secret",
    "type": "java.lang.String",
    "description": "A description for 'app.token-secret'"
  },
  {
    "name": "app.token-expiration-msec",
    "type": "java.lang.String",
    "description": "A description for 'app.token-expiration-msec'"
  },
  {
    "name": "app.cookie-name",
    "type": "java.lang.String",
    "description": "A description for 'app.cookie-name'"
  },
  {
    "name": "app.authorized-redirect-uris",
    "type": "java.lang.String",
    "description": "A description for 'app.authorized-redirect-uris'"
  }
]}